za_id_number/__init__.py
za_id_number/constants.py
za_id_number/za_id_number.py
za_id_number-0.1.1.dist-info/METADATA
za_id_number-0.1.1.dist-info/WHEEL
za_id_number-0.1.1.dist-info/licenses/LICENSE
za_id_number-0.1.1.dist-info/RECORD
