Metadata-Version: 2.4
Name: za-id-number
Version: 0.1.1
Summary: South African (RSA/ZA) Identity Number checking and validation library
Author-email: Christo Goosen <christogoosen@gmail.com>
License: MIT
License-File: LICENSE
Keywords: ID Number,South Africa,validation
Classifier: Development Status :: 3 - Alpha
Classifier: Intended Audience :: Developers
Classifier: License :: OSI Approved :: MIT License
Classifier: Natural Language :: English
Classifier: Operating System :: POSIX :: BSD :: FreeBSD
Classifier: Operating System :: POSIX :: Linux
Classifier: Operating System :: Unix
Classifier: Programming Language :: Python
Classifier: Programming Language :: Python :: 3
Classifier: Programming Language :: Python :: 3 :: Only
Classifier: Programming Language :: Python :: 3.9
Classifier: Programming Language :: Python :: 3.10
Classifier: Programming Language :: Python :: 3.11
Classifier: Programming Language :: Python :: 3.12
Classifier: Programming Language :: Python :: 3.13
Classifier: Topic :: Software Development
Classifier: Typing :: Typed
Requires-Python: <4,>=3.9.0
Requires-Dist: luhn<0.3,>=0.2.0
